lightning_ir/__init__.py
lightning_ir/__main__.py
lightning_ir/main.py
lightning_ir/base/__init__.py
lightning_ir/base/adapter.py
lightning_ir/base/class_factory.py
lightning_ir/base/config.py
lightning_ir/base/external_model_hub.py
lightning_ir/base/model.py
lightning_ir/base/module.py
lightning_ir/base/tokenizer.py
lightning_ir/base/validation_utils.py
lightning_ir/bi_encoder/__init__.py
lightning_ir/bi_encoder/bi_encoder_config.py
lightning_ir/bi_encoder/bi_encoder_model.py
lightning_ir/bi_encoder/bi_encoder_module.py
lightning_ir/bi_encoder/bi_encoder_tokenizer.py
lightning_ir/callbacks/__init__.py
lightning_ir/callbacks/callbacks.py
lightning_ir/cross_encoder/__init__.py
lightning_ir/cross_encoder/cross_encoder_config.py
lightning_ir/cross_encoder/cross_encoder_model.py
lightning_ir/cross_encoder/cross_encoder_module.py
lightning_ir/cross_encoder/cross_encoder_tokenizer.py
lightning_ir/data/__init__.py
lightning_ir/data/data.py
lightning_ir/data/datamodule.py
lightning_ir/data/dataset.py
lightning_ir/data/external_datasets/__init__.py
lightning_ir/data/external_datasets/colbert.py
lightning_ir/data/external_datasets/cross_architecture_knowledge_distillation.py
lightning_ir/data/external_datasets/ir_datasets_utils.py
lightning_ir/data/external_datasets/rank_distillm.py
lightning_ir/data/external_datasets/sbert.py
lightning_ir/loss/__init__.py
lightning_ir/loss/approximate.py
lightning_ir/loss/base.py
lightning_ir/loss/embedding.py
lightning_ir/loss/in_batch.py
lightning_ir/loss/listwise.py
lightning_ir/loss/neural.py
lightning_ir/loss/pairwise.py
lightning_ir/loss/regularization.py
lightning_ir/modeling_utils/__init__.py
lightning_ir/modeling_utils/batching.py
lightning_ir/modeling_utils/embedding_post_processing.py
lightning_ir/modeling_utils/mlm_head.py
lightning_ir/models/__init__.py
lightning_ir/models/register_external_models.py
lightning_ir/models/register_internal_models.py
lightning_ir/models/bi_encoders/__init__.py
lightning_ir-0.0.6.dist-info/licenses/LICENSE
lightning_ir-0.0.6.dist-info/METADATA
lightning_ir-0.0.6.dist-info/WHEEL
lightning_ir-0.0.6.dist-info/entry_points.txt
lightning_ir-0.0.6.dist-info/top_level.txt
lightning_ir-0.0.6.dist-info/RECORD
