Metadata-Version: 2.4
Name: lightning-ir
Version: 0.0.6
Summary: Your one-stop shop for fine-tuning and running neural ranking models.
Author-email: Ferdinand Schlatt <ferdinand.schlatt@uni-jena.de>
License: Apache-2.0
Keywords: information-retrieval
Classifier: Programming Language :: Python :: 3
Classifier: Programming Language :: Python :: 3 :: Only
Classifier: Programming Language :: Python :: 3.9
Classifier: Programming Language :: Python :: 3.10
Classifier: Programming Language :: Python :: 3.11
Classifier: Programming Language :: Python :: 3.12
Classifier: Programming Language :: Python :: 3.13
Classifier: Topic :: Scientific/Engineering
Requires-Python: >=3.9
License-File: LICENSE
Requires-Dist: transformers[torch]>=4.50.0
Requires-Dist: datasets>=3.0.0
Requires-Dist: ir_datasets
Requires-Dist: ir-measures
Requires-Dist: lightning
Requires-Dist: pandas
Requires-Dist: jsonargparse[signatures]>=4.27.7
Requires-Dist: sentencepiece
Requires-Dist: protobuf
Provides-Extra: test
Requires-Dist: pytest<10,>=8; extra == "test"
Requires-Dist: pytest-cov<8,>=5; extra == "test"
Requires-Dist: sentence-transformers; extra == "test"
Requires-Dist: faiss-cpu; extra == "test"
Requires-Dist: pyseismic-lsr; extra == "test"
Requires-Dist: omegaconf; extra == "test"
Requires-Dist: colbert-ai; extra == "test"
Requires-Dist: fast-plaid; extra == "test"
Provides-Extra: adapters
Requires-Dist: peft>=0.17.0; extra == "adapters"
Provides-Extra: dev
Requires-Dist: ruff; extra == "dev"
Provides-Extra: docs
Requires-Dist: sphinx; extra == "docs"
Requires-Dist: myst-parser; extra == "docs"
Requires-Dist: sphinxawesome-theme; extra == "docs"
Requires-Dist: sphinx-toolbox; extra == "docs"
Dynamic: license-file
